module.py
instra_together-0.0.1.dist-info/METADATA
instra_together-0.0.1.dist-info/WHEEL
instra_together-0.0.1.dist-info/top_level.txt
instra_together-0.0.1.dist-info/RECORD
